syndb_constants/__init__.py
syndb_constants/app.py
syndb_constants/data_license.py
syndb_constants/dataset.py
syndb_constants/schema.py
syndb_constants/table.py
syndb_constants-0.17.0.dist-info/METADATA
syndb_constants-0.17.0.dist-info/WHEEL
syndb_constants-0.17.0.dist-info/RECORD
