Metadata-Version: 2.4
Name: syndb-constants
Version: 0.17.0
Summary: Constants used with SynDB in Python
Author-email: caniko <git@rotas.mozmail.com>
License-Expression: MIT
Requires-Python: <4.0,>=3.9
